machinist/_version.py
machinist/__init__.py
machinist/_logging.py
machinist/_interface.py
machinist/_fsm.py
machinist/test/__init__.py
machinist/test/test_fsm.py
machinist/test/loglib.py
machinist-0.2.0.dist-info/METADATA
machinist-0.2.0.dist-info/metadata.json
machinist-0.2.0.dist-info/RECORD
machinist-0.2.0.dist-info/top_level.txt
machinist-0.2.0.dist-info/WHEEL
machinist-0.2.0.dist-info/DESCRIPTION.rst
